MANIFEST.in
requirements.txt
setup.py
bin/streaming-kmeans
mlstreaming/__init__.py
mlstreaming/base.py
mlstreaming/kmeans.py
mlstreaming/util.py
mlstreaming/lib/__init__.py
mlstreaming/lib/spark-ml-streaming_2.10-0.1.0.jar
spark_ml_streaming.egg-info/PKG-INFO
spark_ml_streaming.egg-info/SOURCES.txt
spark_ml_streaming.egg-info/dependency_links.txt
spark_ml_streaming.egg-info/requires.txt
spark_ml_streaming.egg-info/top_level.txt