Metadata-Version: 1.0
Name: spark-ml-streaming
Version: 0.1.0
Summary: A Python library for visualizing streaming machine learning in Spark
Home-page: https://github.com/freeman-lab/spark-ml-streaming
Author: Jeremy Freeman
Author-email: the.freeman.lab@gmail.com
License: UNKNOWN
Platform: UNKNOWN
